odoo10_addon_l10n_fr_fec_oca-10.0.1.0.0.99.dev4-py3.8-nspkg.pth
odoo/addons/l10n_fr_fec_oca/README.rst
odoo/addons/l10n_fr_fec_oca/__init__.py
odoo/addons/l10n_fr_fec_oca/__manifest__.py
odoo/addons/l10n_fr_fec_oca/i18n/fr.po
odoo/addons/l10n_fr_fec_oca/i18n/l10n_fr_fec.pot
odoo/addons/l10n_fr_fec_oca/i18n/l10n_fr_fec_oca.pot
odoo/addons/l10n_fr_fec_oca/readme/CONTRIBUTORS.rst
odoo/addons/l10n_fr_fec_oca/readme/DESCRIPTION.rst
odoo/addons/l10n_fr_fec_oca/readme/USAGE.rst
odoo/addons/l10n_fr_fec_oca/static/description/icon.png
odoo/addons/l10n_fr_fec_oca/static/description/index.html
odoo/addons/l10n_fr_fec_oca/wizard/__init__.py
odoo/addons/l10n_fr_fec_oca/wizard/account_fr_fec_oca.py
odoo/addons/l10n_fr_fec_oca/wizard/account_fr_fec_oca_view.xml
odoo10_addon_l10n_fr_fec_oca-10.0.1.0.0.99.dev4.dist-info/METADATA
odoo10_addon_l10n_fr_fec_oca-10.0.1.0.0.99.dev4.dist-info/WHEEL
odoo10_addon_l10n_fr_fec_oca-10.0.1.0.0.99.dev4.dist-info/namespace_packages.txt
odoo10_addon_l10n_fr_fec_oca-10.0.1.0.0.99.dev4.dist-info/top_level.txt
odoo10_addon_l10n_fr_fec_oca-10.0.1.0.0.99.dev4.dist-info/RECORD
