Metadata-Version: 2.1
Name: odoo10-addon-l10n-fr-fec-oca
Version: 10.0.1.0.0.99.dev4
Summary: Fichier d'Échange Informatisé (FEC) for France
Home-page: https://github.com/OCA/l10n-france
Author: Akretion,Odoo SA,Odoo Community Association (OCA)
Author-email: support@odoo-community.org
License: LGPL-3
Platform: UNKNOWN
Classifier: Programming Language :: Python
Classifier: Framework :: Odoo
Classifier: Framework :: Odoo :: 10.0
Classifier: License :: OSI Approved :: GNU Lesser General Public License v3 (LGPLv3)
Requires-Python: ~=2.7
Requires-Dist: odoo10-addon-date-range
Requires-Dist: odoo <10.1dev,>=10.0
Requires-Dist: unicodecsv
Requires-Dist: unidecode
